{
  "docs": [
    {
      "type": "link",
      "collapsed": false,
      "label": "Welcome",
      "href": "/docs/"
    },
    {
      "type": "category",
      "label": "How-tos",
      "items": [
        {
          "type": "link",
          "collapsed": false,
          "label": "Store",
          "href": "/docs/how-tos/store"
        },
        {
          "type": "link",
          "collapsed": false,
          "label": "Retrieve",
          "href": "/docs/how-tos/retrieve"
        },
        {
          "type": "link",
          "collapsed": false,
          "label": "Query",
          "href": "/docs/how-tos/query"
        },
        {
          "type": "link",
          "collapsed": false,
          "label": "List",
          "href": "/docs/how-tos/list"
        },
        {
          "type": "link",
          "collapsed": false,
          "label": "List directory contents",
          "href": "/docs/how-tos/list-directory-contents"
        },
        {
          "type": "link",
          "collapsed": false,
          "label": "Work with Content Archives",
          "href": "/docs/how-tos/work-with-car-files"
        },
        {
          "type": "link",
          "collapsed": false,
          "label": "Generate an API token",
          "href": "/docs/how-tos/generate-api-token"
        },
        {
          "type": "link",
          "collapsed": false,
          "label": "Troubleshooting",
          "href": "/docs/how-tos/troubleshooting"
        }
      ]
    },
    {
      "type": "category",
      "label": "Concepts",
      "items": [
        {
          "type": "link",
          "collapsed": false,
          "label": "Content addressing",
          "href": "/docs/concepts/content-addressing"
        },
        {
          "type": "link",
          "collapsed": false,
          "label": "Decentralized storage",
          "href": "/docs/concepts/decentralized-storage"
        },
        {
          "type": "link",
          "collapsed": false,
          "label": "Web3.Storage economics",
          "href": "/docs/concepts/storage-economics"
        }
      ]
    },
    {
      "type": "category",
      "label": "Examples",
      "items": [
        {
          "type": "link",
          "collapsed": false,
          "label": "Getting started",
          "href": "/docs/examples/getting-started"
        },
        {
          "type": "link",
          "collapsed": false,
          "label": "Image gallery",
          "href": "/docs/examples/image-gallery"
        }
      ]
    },
    {
      "type": "category",
      "label": "Reference",
      "items": [
        {
          "type": "link",
          "collapsed": false,
          "label": "JavaScript client library",
          "href": "/docs/reference/js-client-library"
        },
        {
          "type": "link",
          "collapsed": false,
          "label": "JavaScript utility libraries",
          "href": "/docs/reference/js-utilities"
        },
        {
          "type": "link",
          "collapsed": false,
          "label": "Go client library",
          "href": "/docs/reference/go-client-library"
        },
        {
          "type": "link",
          "label": "HTTP API",
          "href": "/reference/http-api/"
        }
      ]
    },
    {
      "type": "category",
      "label": "Community",
      "items": [
        {
          "type": "link",
          "collapsed": false,
          "label": "Help & support",
          "href": "/docs/community/help-and-support"
        }
      ]
    }
  ]
}